odoo/addons/helpdesk_mgmt_partner_sequence/README.rst
odoo/addons/helpdesk_mgmt_partner_sequence/__init__.py
odoo/addons/helpdesk_mgmt_partner_sequence/__manifest__.py
odoo/addons/helpdesk_mgmt_partner_sequence/demo/helpdesk_demo.xml
odoo/addons/helpdesk_mgmt_partner_sequence/i18n/es.po
odoo/addons/helpdesk_mgmt_partner_sequence/i18n/es_ES.po
odoo/addons/helpdesk_mgmt_partner_sequence/i18n/fr.po
odoo/addons/helpdesk_mgmt_partner_sequence/i18n/helpdesk_mgmt_partner_sequence.pot
odoo/addons/helpdesk_mgmt_partner_sequence/i18n/pt_BR.po
odoo/addons/helpdesk_mgmt_partner_sequence/models/__init__.py
odoo/addons/helpdesk_mgmt_partner_sequence/models/helpdesk_ticket.py
odoo/addons/helpdesk_mgmt_partner_sequence/models/res_partner.py
odoo/addons/helpdesk_mgmt_partner_sequence/readme/CONTRIBUTORS.rst
odoo/addons/helpdesk_mgmt_partner_sequence/readme/DESCRIPTION.rst
odoo/addons/helpdesk_mgmt_partner_sequence/static/description/icon.png
odoo/addons/helpdesk_mgmt_partner_sequence/static/description/index.html
odoo/addons/helpdesk_mgmt_partner_sequence/tests/__init__.py
odoo/addons/helpdesk_mgmt_partner_sequence/tests/test_helpdesk_ticket.py
odoo/addons/helpdesk_mgmt_partner_sequence/views/res_partner_view.xml
odoo12_addon_helpdesk_mgmt_partner_sequence-12.0.1.0.0.99.dev12.dist-info/METADATA
odoo12_addon_helpdesk_mgmt_partner_sequence-12.0.1.0.0.99.dev12.dist-info/WHEEL
odoo12_addon_helpdesk_mgmt_partner_sequence-12.0.1.0.0.99.dev12.dist-info/top_level.txt
odoo12_addon_helpdesk_mgmt_partner_sequence-12.0.1.0.0.99.dev12.dist-info/RECORD
